{
	"cid": "菜谱",
	"content": [{
			"name": "酸辣土豆丝",
			"goods": [
				"土豆",
				"辣椒"
			],
			"method": "炒",
			"time": 15
		},
		{
			"name": "葱爆虾仁",
			"goods": [
				"虾仁",
				"香葱"
			],
			"method": "炒",
			"time": 18
		},
		{
			"name": "凉拌黄瓜",
			"goods": [
				"黄瓜"
			],
			"method": "拌",
			"time": 8
		},
		{
			"name": "蒸鸡蛋羹",
			"goods": [
				"鸡蛋"
			],
			"method": "蒸",
			"time": 28
		},
		{
			"name": "辣椒炒肉",
			"goods": [
				"辣椒",
				"猪肉"
			],
			"method": "炒",
			"time": 25
		},
		{
			"name": "凉拌西红柿",
			"goods": [
				"西红柿"
			],
			"method": "拌",
			"time": 10
		}
	]
}